libname/__init__.py
libname/hello.py
hallomoshe-0.0.1.dist-info/METADATA
hallomoshe-0.0.1.dist-info/WHEEL
hallomoshe-0.0.1.dist-info/top_level.txt
hallomoshe-0.0.1.dist-info/RECORD
