Metadata-Version: 2.1
Name: hallomoshe
Version: 0.0.1
Summary: say hello and bay
Home-page: UNKNOWN
Author: moshe rosenblum
Author-email: mosherosenblum1@gmail.com
License: UNKNOWN
Keywords: python,video,stream,video stream,camera stream,sockets
Platform: UNKNOWN
Classifier: Development Status :: 1 - Planning
Classifier: Intended Audience :: Developers
Classifier: Programming Language :: Python :: 3
Classifier: Operating System :: Unix
Classifier: Operating System :: MacOS :: MacOS X
Classifier: Operating System :: Microsoft :: Windows
